yt_fts/__init__.py
yt_fts/config.py
yt_fts/db_utils.py
yt_fts/export.py
yt_fts/list.py
yt_fts/search.py
yt_fts/utils.py
yt_fts/yt_fts.py
yt_fts/download/__init__.py
yt_fts/download/download_handler.py
yt_fts/llm/__init__.py
yt_fts/llm/chatbot.py
yt_fts/llm/get_embeddings.py
yt_fts/llm/summarize.py
yt_fts-0.1.62.dist-info/licenses/LICENSE
yt_fts-0.1.62.dist-info/METADATA
yt_fts-0.1.62.dist-info/WHEEL
yt_fts-0.1.62.dist-info/entry_points.txt
yt_fts-0.1.62.dist-info/top_level.txt
yt_fts-0.1.62.dist-info/RECORD
