Metadata-Version: 2.4
Name: yt-fts
Version: 0.1.62
Summary: Search all of a YouTube channel from the command line
Author-email: NotJoeMartinez <notjoemartinez@protonmail.com>
License: This is free and unencumbered software released into the public domain.
Project-URL: Homepage, https://github.com/NotJoeMartinez/yt-fts
Keywords: youtube,subtitles,search
Classifier: Programming Language :: Python :: 3.10
Classifier: License :: OSI Approved :: The Unlicense (Unlicense)
Classifier: Operating System :: OS Independent
Requires-Python: >=3.10
License-File: LICENSE
Requires-Dist: click==8.1.7
Requires-Dist: openai==1.93.0
Requires-Dist: chromadb==1.0.15
Requires-Dist: requests<3,>=2.32.2
Requires-Dist: rich==13.7.1
Requires-Dist: sqlite-utils==3.36
Requires-Dist: beautifulsoup4==4.12.3
Requires-Dist: yt-dlp==2025.6.30
Requires-Dist: webvtt-py==0.5.1
Dynamic: license-file
